yinian_mcp_server_demo/__init__.py
yinian_mcp_server_demo-0.1.0.dist-info/METADATA
yinian_mcp_server_demo-0.1.0.dist-info/WHEEL
yinian_mcp_server_demo-0.1.0.dist-info/entry_points.txt
yinian_mcp_server_demo-0.1.0.dist-info/RECORD
