Metadata-Version: 2.4
Name: yinian-mcp-server-demo
Version: 0.1.0
Summary: Add your description here
Author-email: 泡椒 <1062788706@qq.com>
Requires-Python: >=3.13
Requires-Dist: mcp[cli]>=1.11.0
